.gitignore
MANIFEST.in
README.rst
setup.py
coop_cms/__init__.py
coop_cms/admin.py
coop_cms/coop_bar_cfg.py
coop_cms/forms.py
coop_cms/html2text.py
coop_cms/models.py
coop_cms/perms_backends.py
coop_cms/settings.py
coop_cms/tests.py
coop_cms/urls.py
coop_cms/utils.py
coop_cms/views.py
coop_cms/widgets.py
coop_cms.egg-info/PKG-INFO
coop_cms.egg-info/SOURCES.txt
coop_cms.egg-info/dependency_links.txt
coop_cms.egg-info/not-zip-safe
coop_cms.egg-info/requires.txt
coop_cms.egg-info/top_level.txt
coop_cms/apps/__init__.py
coop_cms/apps/basic_cms/__init__.py
coop_cms/apps/basic_cms/models.py
coop_cms/apps/basic_cms/tests.py
coop_cms/apps/basic_cms/migrations/0001_initial.py
coop_cms/apps/basic_cms/migrations/0002_article_is_homepage.py
coop_cms/apps/basic_cms/migrations/0003_htmlfield_removed.py
coop_cms/apps/basic_cms/migrations/0004_auto__add_navtree__add_field_article_headline__chg_field_article_slug.py
coop_cms/apps/basic_cms/migrations/__init__.py
coop_cms/apps/demo_cms/__init__.py
coop_cms/apps/demo_cms/admin.py
coop_cms/apps/demo_cms/coop_cms_settings.py
coop_cms/apps/demo_cms/forms.py
coop_cms/apps/demo_cms/models.py
coop_cms/apps/demo_cms/my_coop_bar.py
coop_cms/apps/demo_cms/tests.py
coop_cms/apps/demo_cms/migrations/0001_initial.py
coop_cms/apps/demo_cms/migrations/0002_auto__add_field_article_in_newsletter.py
coop_cms/apps/demo_cms/migrations/0003_article_is_homepage.py
coop_cms/apps/demo_cms/migrations/0004_htmlfield_removed.py
coop_cms/apps/demo_cms/migrations/0005_auto__add_field_article_headline.py
coop_cms/apps/demo_cms/migrations/__init__.py
coop_cms/apps/demo_cms/static/css/demo-style.css
coop_cms/apps/demo_cms/static/js/jquery.sortElements.js
coop_cms/apps/demo_cms/templates/404.html
coop_cms/apps/demo_cms/templates/500.html
coop_cms/apps/demo_cms/templates/base.html
coop_cms/apps/demo_cms/templates/basic_newsletter.html
coop_cms/apps/demo_cms/templates/blog.html
coop_cms/apps/demo_cms/templates/homepage.html
coop_cms/apps/demo_cms/templates/sortable_newsletter.html
coop_cms/apps/demo_cms/templates/special_newsletter.html
coop_cms/apps/demo_cms/templates/standard.html
coop_cms/apps/demo_cms/templates/standard_en.html
