Metadata-Version: 1.0
Name: coop-cms
Version: 0.7.0
Summary: Small CMS built around a tree navigation open to any django models
Home-page: https://github.com/quinode/coop_cms/
Author: Luc Jean
Author-email: ljean@apidev.fr
License: BSD
Download-URL: https://github.com/quinode/coop_cms/tarball/master
Platform: UNKNOWN
Classifier: Development Status :: 4 - Beta
Classifier: Environment :: Web Environment
Classifier: Intended Audience :: Developers
Classifier: License :: OSI Approved :: BSD License
Classifier: Operating System :: OS Independent
Classifier: Programming Language :: Python
Classifier: Framework :: Django
Classifier: Natural Language :: English
Classifier: Natural Language :: French
Classifier: Topic :: Internet :: WWW/HTTP :: Dynamic Content
Classifier: Topic :: Internet :: WWW/HTTP :: WSGI :: Application
